[{"countryCode": "BRA", "indicatorCode": "NE.EXP.GNFS.ZS", "time": "2021", "value": 20.0972752064931}, {"countryCode": "BRA", "indicatorCode": "NE.EXP.GNFS.ZS", "time": "2020", "value": 16.795068432705}, {"countryCode": "BRA", "indicatorCode": "NE.EXP.GNFS.ZS", "time": "2019", "value": 14.122919190471}, {"countryCode": "BRA", "indicatorCode": "NE.EXP.GNFS.ZS", "time": "2018", "value": 14.6349994949752}, {"countryCode": "BRA", "indicatorCode": "NE.EXP.GNFS.ZS", "time": "2017", "value": 12.518967870078}, {"countryCode": "BRA", "indicatorCode": "NE.EXP.GNFS.ZS", "time": "2016", "value": 12.466679044149}, {"countryCode": "BRA", "indicatorCode": "NE.EXP.GNFS.ZS", "time": "2015", "value": 12.9001914182073}, {"countryCode": "BRA", "indicatorCode": "NE.EXP.GNFS.ZS", "time": "2014", "value": 11.0119428229537}, {"countryCode": "BRA", "indicatorCode": "NE.EXP.GNFS.ZS", "time": "2013", "value": 11.7422306424698}, {"countryCode": "BRA", "indicatorCode": "NE.EXP.GNFS.ZS", "time": "2012", "value": 11.8775390682698}, {"countryCode": "BRA", "indicatorCode": "NE.EXP.GNFS.ZS", "time": "2011", "value": 11.582512675751}, {"countryCode": "BRA", "indicatorCode": "NE.EXP.GNFS.ZS", "time": "2010", "value": 10.8655847744861}, {"countryCode": "CHN", "indicatorCode": "NE.EXP.GNFS.ZS", "time": "2021", "value": 20.0098140678205}, {"countryCode": "CHN", "indicatorCode": "NE.EXP.GNFS.ZS", "time": "2020", "value": 18.541060011129}, {"countryCode": "CHN", "indicatorCode": "NE.EXP.GNFS.ZS", "time": "2019", "value": 18.4099923154801}, {"countryCode": "CHN", "indicatorCode": "NE.EXP.GNFS.ZS", "time": "2018", "value": 19.1121035364139}, {"countryCode": "CHN", "indicatorCode": "NE.EXP.GNFS.ZS", "time": "2017", "value": 19.6922769882201}, {"countryCode": "CHN", "indicatorCode": "NE.EXP.GNFS.ZS", "time": "2016", "value": 19.5843800536482}, {"countryCode": "CHN", "indicatorCode": "NE.EXP.GNFS.ZS", "time": "2015", "value": 21.3540798828848}, {"countryCode": "CHN", "indicatorCode": "NE.EXP.GNFS.ZS", "time": "2014", "value": 23.5100609074235}, {"countryCode": "CHN", "indicatorCode": "NE.EXP.GNFS.ZS", "time": "2013", "value": 24.599254436897}, {"countryCode": "CHN", "indicatorCode": "NE.EXP.GNFS.ZS", "time": "2012", "value": 25.4925222245396}, {"countryCode": "CHN", "indicatorCode": "NE.EXP.GNFS.ZS", "time": "2011", "value": 26.5681893451605}, {"countryCode": "CHN", "indicatorCode": "NE.EXP.GNFS.ZS", "time": "2010", "value": 27.1853327204051}, {"countryCode": "IND", "indicatorCode": "NE.EXP.GNFS.ZS", "time": "2021", "value": 20.8136349598302}, {"countryCode": "IND", "indicatorCode": "NE.EXP.GNFS.ZS", "time": "2020", "value": 18.7088986865584}, {"countryCode": "IND", "indicatorCode": "NE.EXP.GNFS.ZS", "time": "2019", "value": 18.6909827074089}, {"countryCode": "IND", "indicatorCode": "NE.EXP.GNFS.ZS", "time": "2018", "value": 19.9278285988562}, {"countryCode": "IND", "indicatorCode": "NE.EXP.GNFS.ZS", "time": "2017", "value": 18.7917648392982}, {"countryCode": "IND", "indicatorCode": "NE.EXP.GNFS.ZS", "time": "2016", "value": 19.1582349105946}, {"countryCode": "IND", "indicatorCode": "NE.EXP.GNFS.ZS", "time": "2015", "value": 19.8131891564045}, {"countryCode": "IND", "indicatorCode": "NE.EXP.GNFS.ZS", "time": "2014", "value": 22.9679630081172}, {"countryCode": "IND", "indicatorCode": "NE.EXP.GNFS.ZS", "time": "2013", "value": 25.430861300519}, {"countryCode": "IND", "indicatorCode": "NE.EXP.GNFS.ZS", "time": "2012", "value": 24.534430661418}, {"countryCode": "IND", "indicatorCode": "NE.EXP.GNFS.ZS", "time": "2011", "value": 24.5404113195713}, {"countryCode": "IND", "indicatorCode": "NE.EXP.GNFS.ZS", "time": "2010", "value": 22.4009332488238}, {"countryCode": "MEX", "indicatorCode": "NE.EXP.GNFS.ZS", "time": "2021", "value": 40.4297423970169}, {"countryCode": "MEX", "indicatorCode": "NE.EXP.GNFS.ZS", "time": "2020", "value": 39.6030465121765}, {"countryCode": "MEX", "indicatorCode": "NE.EXP.GNFS.ZS", "time": "2019", "value": 38.8092813307908}, {"countryCode": "MEX", "indicatorCode": "NE.EXP.GNFS.ZS", "time": "2018", "value": 39.2575517289021}, {"countryCode": "MEX", "indicatorCode": "NE.EXP.GNFS.ZS", "time": "2017", "value": 37.6515684577081}, {"countryCode": "MEX", "indicatorCode": "NE.EXP.GNFS.ZS", "time": "2016", "value": 37.0421710841871}, {"countryCode": "MEX", "indicatorCode": "NE.EXP.GNFS.ZS", "time": "2015", "value": 34.5248858421072}, {"countryCode": "MEX", "indicatorCode": "NE.EXP.GNFS.ZS", "time": "2014", "value": 31.8734413093812}, {"countryCode": "MEX", "indicatorCode": "NE.EXP.GNFS.ZS", "time": "2013", "value": 31.3056529459396}, {"countryCode": "MEX", "indicatorCode": "NE.EXP.GNFS.ZS", "time": "2012", "value": 32.2655677637235}, {"countryCode": "MEX", "indicatorCode": "NE.EXP.GNFS.ZS", "time": "2011", "value": 31.0367071399496}, {"countryCode": "MEX", "indicatorCode": "NE.EXP.GNFS.ZS", "time": "2010", "value": 29.6976647689721}, {"countryCode": "TUR", "indicatorCode": "NE.EXP.GNFS.ZS", "time": "2021", "value": 35.3956283335292}, {"countryCode": "TUR", "indicatorCode": "NE.EXP.GNFS.ZS", "time": "2020", "value": 28.6648560112337}, {"countryCode": "TUR", "indicatorCode": "NE.EXP.GNFS.ZS", "time": "2019", "value": 32.5973545785751}, {"countryCode": "TUR", "indicatorCode": "NE.EXP.GNFS.ZS", "time": "2018", "value": 31.1528780424886}, {"countryCode": "TUR", "indicatorCode": "NE.EXP.GNFS.ZS", "time": "2017", "value": 26.0394223439924}, {"countryCode": "TUR", "indicatorCode": "NE.EXP.GNFS.ZS", "time": "2016", "value": 23.0835091311263}, {"countryCode": "TUR", "indicatorCode": "NE.EXP.GNFS.ZS", "time": "2015", "value": 24.5312773389092}, {"countryCode": "TUR", "indicatorCode": "NE.EXP.GNFS.ZS", "time": "2014", "value": 25.2055416974053}, {"countryCode": "TUR", "indicatorCode": "NE.EXP.GNFS.ZS", "time": "2013", "value": 23.7930095050818}, {"countryCode": "TUR", "indicatorCode": "NE.EXP.GNFS.ZS", "time": "2012", "value": 24.3608755208614}, {"countryCode": "TUR", "indicatorCode": "NE.EXP.GNFS.ZS", "time": "2011", "value": 22.9937012536403}, {"countryCode": "TUR", "indicatorCode": "NE.EXP.GNFS.ZS", "time": "2010", "value": 21.1941333155525}, {"countryCode": "ZAF", "indicatorCode": "NE.EXP.GNFS.ZS", "time": "2021", "value": 31.1077352259717}, {"countryCode": "ZAF", "indicatorCode": "NE.EXP.GNFS.ZS", "time": "2020", "value": 27.778011440401}, {"countryCode": "ZAF", "indicatorCode": "NE.EXP.GNFS.ZS", "time": "2019", "value": 27.3421804922648}, {"countryCode": "ZAF", "indicatorCode": "NE.EXP.GNFS.ZS", "time": "2018", "value": 27.4885881268174}, {"countryCode": "ZAF", "indicatorCode": "NE.EXP.GNFS.ZS", "time": "2017", "value": 27.3400757812216}, {"countryCode": "ZAF", "indicatorCode": "NE.EXP.GNFS.ZS", "time": "2016", "value": 28.1560881698955}, {"countryCode": "ZAF", "indicatorCode": "NE.EXP.GNFS.ZS", "time": "2015", "value": 27.7136384124829}, {"countryCode": "ZAF", "indicatorCode": "NE.EXP.GNFS.ZS", "time": "2014", "value": 29.0006193033471}, {"countryCode": "ZAF", "indicatorCode": "NE.EXP.GNFS.ZS", "time": "2013", "value": 28.379280320361}, {"countryCode": "ZAF", "indicatorCode": "NE.EXP.GNFS.ZS", "time": "2012", "value": 27.1391491937679}, {"countryCode": "ZAF", "indicatorCode": "NE.EXP.GNFS.ZS", "time": "2011", "value": 27.6981484703752}, {"countryCode": "ZAF", "indicatorCode": "NE.EXP.GNFS.ZS", "time": "2010", "value": 25.7834176267221}]